snakemake_executor_plugin_aws_batch/__init__.py
snakemake_executor_plugin_aws_batch/batch_client.py
snakemake_executor_plugin_aws_batch/batch_job_builder.py
snakemake_executor_plugin_aws_batch/constant.py
snakemake_executor_plugin_aws_batch-0.2.1.dist-info/LICENSE
snakemake_executor_plugin_aws_batch-0.2.1.dist-info/METADATA
snakemake_executor_plugin_aws_batch-0.2.1.dist-info/WHEEL
snakemake_executor_plugin_aws_batch-0.2.1.dist-info/RECORD
